{
    "type": "FeatureCollection",
    "features": [
      {
        "type": "Feature",
        "properties": {
          "stroke": "#555555",
          "stroke-width": 2,
          "stroke-opacity": 1,
          "punto_di_partenza": "A",
          "punto_di_arrivo": "B"
        },
        "geometry": {
          "type": "LineString",
          "coordinates": [
            [
              7.884825468063355,
              45.47508135410783
            ],
            [
              7.884610891342162,
              45.47506630756987
            ],
            [
              7.884546518325806,
              45.47490079538709
            ],
            [
              7.884471416473389,
              45.47472775940352
            ],
            [
              7.884482145309447,
              45.47466757284988
            ],
            [
              7.8846752643585205,
              45.47466757284988
            ],
            [
              7.884911298751831,
              45.474652526201446
            ],
            [
              7.8851258754730225,
              45.47451710618464
            ],
            [
              7.885276079177856,
              45.47445691940605
            ],
            [
              7.885587215423584,
              45.47455472288862
            ],
            [
              7.885844707489013,
              45.47463747954898
            ],
            [
              7.88618803024292,
              45.474607386232
            ],
            [
              7.886606454849243,
              45.4747352827182
            ],
            [
              7.887196540832519,
              45.474908318678665
            ],
            [
              7.887572050094604,
              45.47490079538709
            ],
            [
              7.887979745864867,
              45.474870702210715
            ],
            [
              7.888365983963013,
              45.47496098169163
            ],
            [
              7.888741493225098,
              45.474908318678665
            ],
            [
              7.888827323913574,
              45.47478042258518
            ],
            [
              7.888709306716919,
              45.47466757284988
            ],
            [
              7.888526916503907,
              45.47451710618464
            ],
            [
              7.888387441635131,
              45.47435159238884
            ]
          ]
        }
      }
    ]
  }